{"VUBhmv4BAyFLgVrFE8kezA==":"background1.jpg","ALDjNyX+JE2bbl5Vmp3u1w==":"background3.jpg","3TkDReVf27ZI6/gnJLLrpQ==":"background4.jpg","GH9OI5hPPTL19Pxpv8K/BA==":"signature.png","Q2qFuEobeLmFw0ZQ1vWDlw==":"background2.jpg","ImE7HEp78Gs1ygqjlr6YKQ==":"01.jpg","kNcDrbHZcDjHQgpqE79vNQ==":"background5.jpg","jrrV4a800+cJsyqItTJbtg==":"02.jpg","AhziEfFfx2MHg3Elnf5sQQ==":"03.jpg","UmOqk0tlyaqlKURWeVqUwQ==":"1.png","SAZ8a+B3RJiYXExxgw/Uww==":"2.png","eFcuBC02POB2tvyFmpwyoA==":"3.png","3Mx0GNYqiu916VUvsN+tgA==":"4.png","jsePuIpB1yHPMRMG9eMrXQ==":"0-546x111.png","2MXQbV3Y2l1mFG7P+CT3Lw==":"amita-holistic-stress-anxiety-panorama-1248x624.jpg","IYrxGiXr3/b+IrNo17pOzg==":"photo_2020-05-31_14-54-17-768x768.jpg","gs9MAIX0M9S2gvZQrXlIpQ==":"photo_2020-05-31_14-54-14-768x432.jpeg","jKZYMm35efGgRpMVfTgkyg==":"photo_2020-05-15_23-47-31-768x1024.jpg","23kScOXgR4rj1B2VDQTGBQ==":"mbr-1252x835.jpg","P9PVB0yomnyefe7uGDEXUg==":"mbr-1252x838.jpg","5mVh5H4slfNN1qX2aZAHtw==":"mbr-400x267.jpg"}